Metadata-Version: 2.1
Name: vivarium-convenience
Version: 0.0.3
Summary: provides a vivarium process with a configurable convenience kinetics
Home-page: UNKNOWN
Author: Eran Agmon
Author-email: agmon.eran@gmail.com
License: MIT
Platform: UNKNOWN
